osn_bas/__init__.py
osn_bas/errors.py
osn_bas/types.py
osn_bas/browsers_handler/__init__.py
osn_bas/browsers_handler/_windows.py
osn_bas/browsers_handler/types.py
osn_bas/webdrivers/Chrome.py
osn_bas/webdrivers/Edge.py
osn_bas/webdrivers/FireFox.py
osn_bas/webdrivers/Yandex.py
osn_bas/webdrivers/__init__.py
osn_bas/webdrivers/_functions.py
osn_bas/webdrivers/functions.py
osn_bas/webdrivers/types.py
osn_bas/webdrivers/BaseDriver/__init__.py
osn_bas/webdrivers/BaseDriver/options.py
osn_bas/webdrivers/BaseDriver/protocols.py
osn_bas/webdrivers/BaseDriver/start_args.py
osn_bas/webdrivers/BaseDriver/webdriver.py
osn_bas/webdrivers/BaseDriver/dev_tools/__init__.py
osn_bas/webdrivers/BaseDriver/dev_tools/_utils.py
osn_bas/webdrivers/BaseDriver/dev_tools/errors.py
osn_bas/webdrivers/BaseDriver/dev_tools/manager.py
osn_bas/webdrivers/BaseDriver/dev_tools/utils.py
osn_bas/webdrivers/BaseDriver/dev_tools/domains/__init__.py
osn_bas/webdrivers/BaseDriver/dev_tools/domains/fetch.py
osn_bas/webdrivers/js_scripts/check_element_in_viewport.js
osn_bas/webdrivers/js_scripts/get_document_scroll_size.js
osn_bas/webdrivers/js_scripts/get_element_css.js
osn_bas/webdrivers/js_scripts/get_element_rect_in_viewport.js
osn_bas/webdrivers/js_scripts/get_random_element_point_in_viewport.js
osn_bas/webdrivers/js_scripts/get_viewport_position.js
osn_bas/webdrivers/js_scripts/get_viewport_rect.js
osn_bas/webdrivers/js_scripts/get_viewport_size.js
osn_bas/webdrivers/js_scripts/open_new_tab.js
osn_bas/webdrivers/js_scripts/stop_window_loading.js
osn_bas-2.1.2.dist-info/METADATA
osn_bas-2.1.2.dist-info/WHEEL
osn_bas-2.1.2.dist-info/top_level.txt
osn_bas-2.1.2.dist-info/RECORD
