Metadata-Version: 2.4
Name: osn-bas
Version: 2.1.2
Summary: osn-bas is a Python library for browser automation and web scraping. It supports Chrome, Firefox, Edge, and Yandex, providing a consistent API for managing browser sessions, options, and common actions like scrolling, element interaction, and JavaScript execution. It also facilitates remote webdriver control.
Author: oddshellnick
Author-email: oddshellnick.programming@gmail.com
Requires-Dist: setuptools>=75.8.0
Requires-Dist: selenium>=4.26.1
Requires-Dist: osn-windows-cmd>=1.0.0
Requires-Dist: osn-requests>=1.1.0
Requires-Dist: pywin32>=306
Requires-Dist: pandas>=2.2.3
Requires-Dist: trio>=0.27.0
Dynamic: author
Dynamic: author-email
Dynamic: description
Dynamic: description-content-type
Dynamic: requires-dist
Dynamic: summary
